README.rst
pelican_related.py
setup.py
pelican_related.egg-info/PKG-INFO
pelican_related.egg-info/SOURCES.txt
pelican_related.egg-info/dependency_links.txt
pelican_related.egg-info/requires.txt
pelican_related.egg-info/top_level.txt