Metadata-Version: 1.1
Name: pelican-related
Version: 0.1
Summary: A Pelican plugin to make a list of related posts from your meta tags and settings.
Home-page: https://github.com/wutali/pelican_related
Author: Takahiro Fujiwara
Author-email: email@wuta.li
License: UNKNOWN
Download-URL: https://github.com/wutali/pelican_related/tarball/master
Platform: UNKNOWN
